<?xml version="1.0" encoding="utf-8" ?>
<dwsync>
<file name="banner.jpg" server="ftp.domeneshop.no" local="130283280475418117" remote="130281630600000000" Dst="1" />
<file name="banner2.jpg" server="ftp.domeneshop.no" local="130283280476818197" remote="130281605400000000" Dst="1" />
<file name="behzad.png" server="ftp.domeneshop.no" local="130283280478308282" remote="130283233800000000" Dst="1" />
<file name="footer.jpg" server="ftp.domeneshop.no" local="130283280478808311" remote="130256235000000000" Dst="1" />
<file name="gata.jpg" server="ftp.domeneshop.no" local="130283280482718534" remote="130281610200000000" Dst="1" />
<file name="banner.psd" server="ftp.domeneshop.no" local="130283280485088670" remote="130258771800000000" Dst="1" />
<file name="jens2.png" server="ftp.domeneshop.no" local="130283280485938719" remote="130283233800000000" Dst="1" />
<file name="sondre2.png" server="ftp.domeneshop.no" local="130283280486448748" remote="130283233800000000" Dst="1" />
<file name="torerik.png" server="ftp.domeneshop.no" local="130283280486988779" remote="130283233800000000" Dst="1" />
</dwsync>